amlaidatatests/__init__.py
amlaidatatests/_version.py
amlaidatatests/base.py
amlaidatatests/cli.py
amlaidatatests/config.py
amlaidatatests/connection.py
amlaidatatests/exceptions.py
amlaidatatests/io.py
amlaidatatests/singleton.py
amlaidatatests/test_generators.py
amlaidatatests/utils.py
amlaidatatests/resources/.gitkeep
amlaidatatests/resources/__init__.py
amlaidatatests/resources/country_codes.csv
amlaidatatests/resources/currency_codes.csv
amlaidatatests/resources/region.xml
amlaidatatests/resources/test_descriptions_en_us.csv
amlaidatatests/schema/__init__.py
amlaidatatests/schema/base.py
amlaidatatests/schema/utils.py
amlaidatatests/schema/v1/__init__.py
amlaidatatests/schema/v1/account_party_link.py
amlaidatatests/schema/v1/common.py
amlaidatatests/schema/v1/party.py
amlaidatatests/schema/v1/party_supplementary_data.py
amlaidatatests/schema/v1/risk_case_event.py
amlaidatatests/schema/v1/tables.py
amlaidatatests/schema/v1/transaction.py
amlaidatatests/tests/__init__.py
amlaidatatests/tests/__main__.py
amlaidatatests/tests/common.py
amlaidatatests/tests/conftest.py
amlaidatatests/tests/test_account_party_link.py
amlaidatatests/tests/test_party_supplementary_data_table.py
amlaidatatests/tests/test_party_table.py
amlaidatatests/tests/test_risk_case_event_table.py
amlaidatatests/tests/test_transaction_table.py
amlaidatatests/tests/fixtures/__init__.py
amlaidatatests/tests/fixtures/fixtures.py
amlaidatatests-0.1.16.dist-info/licenses/LICENSE.md
amlaidatatests-0.1.16.dist-info/METADATA
amlaidatatests-0.1.16.dist-info/WHEEL
amlaidatatests-0.1.16.dist-info/entry_points.txt
amlaidatatests-0.1.16.dist-info/top_level.txt
amlaidatatests-0.1.16.dist-info/RECORD
